sklearn_features/__init__.py
sklearn_features/transformers.py
sklearn_features/tests/__init__.py
sklearn_features/tests/test_transformers.py
sklearn_features-0.0.2.dist-info/DESCRIPTION.rst
sklearn_features-0.0.2.dist-info/METADATA
sklearn_features-0.0.2.dist-info/RECORD
sklearn_features-0.0.2.dist-info/WHEEL
sklearn_features-0.0.2.dist-info/metadata.json
sklearn_features-0.0.2.dist-info/top_level.txt
