Metadata-Version: 1.2
Name: sklearn-features
Version: 0.0.2
Summary: Helpful tools for building feature extraction pipelines with scikit-learn
Home-page: https://github.com/sixtwoeight-tech/sklearn-features
Author: UNKNOWN
Author-email: UNKNOWN
License: MIT
Platform: UNKNOWN
Classifier: Development Status :: 2 - Pre-Alpha
Classifier: Intended Audience :: Science/Research
Classifier: License :: OSI Approved :: MIT License
Classifier: Natural Language :: English
Classifier: Programming Language :: Python :: 3
Classifier: Topic :: Scientific/Engineering
Requires-Python: >=3.3
